trio_run_in_process/__init__.py
trio_run_in_process/_child.py
trio_run_in_process/_utils.py
trio_run_in_process/abc.py
trio_run_in_process/exceptions.py
trio_run_in_process/process.py
trio_run_in_process/run_in_process.py
trio_run_in_process/state.py
trio_run_in_process/typing.py
trio_run_in_process-0.1.0a1.dist-info/LICENSE
trio_run_in_process-0.1.0a1.dist-info/METADATA
trio_run_in_process-0.1.0a1.dist-info/WHEEL
trio_run_in_process-0.1.0a1.dist-info/top_level.txt
trio_run_in_process-0.1.0a1.dist-info/RECORD
